MANIFEST.in
README.rst
setup.py
docs/CONTRIBUTORS.rst
docs/HISTORY.rst
docs/LICENSE.GPL
docs/LICENSE.txt
seantis/__init__.py
seantis.people.egg-info/PKG-INFO
seantis.people.egg-info/SOURCES.txt
seantis.people.egg-info/dependency_links.txt
seantis.people.egg-info/entry_points.txt
seantis.people.egg-info/namespace_packages.txt
seantis.people.egg-info/not-zip-safe
seantis.people.egg-info/requires.txt
seantis.people.egg-info/top_level.txt
seantis/people/__init__.py
seantis/people/catalog.py
seantis/people/configure.zcml
seantis/people/errors.py
seantis/people/event_handlers.py
seantis/people/events.py
seantis/people/events.zcml
seantis/people/interfaces.py
seantis/people/profiles.zcml
seantis/people/setuphandler.py
seantis/people/sync.sh
seantis/people/testing.py
seantis/people/upgrades.py
seantis/people/upgrades.zcml
seantis/people/utils.py
seantis/people/behaviors/__init__.py
seantis/people/behaviors/memberships.py
seantis/people/behaviors/name_from_person.py
seantis/people/behaviors/person.py
seantis/people/browser/__init__.py
seantis/people/browser/base.py
seantis/people/browser/configure.zcml
seantis/people/browser/controlpanel.py
seantis/people/browser/export_form.py
seantis/people/browser/import_form.py
seantis/people/browser/json_list.py
seantis/people/browser/layout_policy.py
seantis/people/browser/list.py
seantis/people/browser/macros.py
seantis/people/browser/person.py
seantis/people/browser/renderer.py
seantis/people/browser/js/list-filter.js
seantis/people/browser/templates/controlpanel.pt
seantis/people/browser/templates/list.pt
seantis/people/browser/templates/macros.pt
seantis/people/browser/templates/person.pt
seantis/people/browser/test-views/__init__.py
seantis/people/browser/test-views/load_test_records.py
seantis/people/browser/test-views/load_test_records.xml
seantis/people/content/__init__.py
seantis/people/content/export_content.py
seantis/people/content/import_content.py
seantis/people/content/list.py
seantis/people/content/membership.py
seantis/people/locales/seantis.people.pot
seantis/people/locales/de/LC_MESSAGES/plone.po
seantis/people/locales/de/LC_MESSAGES/seantis.people.po
seantis/people/profiles/default/browserlayer.xml
seantis/people/profiles/default/controlpanel.xml
seantis/people/profiles/default/jsregistry.xml
