Metadata-Version: 1.1
Name: seantis.people
Version: 1.1
Summary: A list of people, optionally organized by organizations and positions.
Home-page: https://github.com/seantis/seantis.people
Author: Seantis GmbH
Author-email: info@seantis.ch
License: GPL v2
Keywords: plone seantis people persons organizations positions
Platform: UNKNOWN
Classifier: Framework :: Plone
Classifier: Framework :: Plone :: 4.3
Classifier: Intended Audience :: Developers
Classifier: Topic :: Software Development :: Libraries :: Python Modules
Classifier: Programming Language :: Python
Classifier: Programming Language :: Python :: 2.7
